kazeflow/__init__.py
kazeflow/assets.py
kazeflow/flow.py
kazeflow/logger.py
kazeflow/partition.py
kazeflow/py.typed
kazeflow/tui.py
kazeflow-0.1.0a2.dist-info/WHEEL
kazeflow-0.1.0a2.dist-info/METADATA
kazeflow-0.1.0a2.dist-info/RECORD
