Metadata-Version: 2.3
Name: kazeflow
Version: 0.1.0a2
Summary: A lightweight, asset-based task flow engine
Author: Kj
Author-email: Kj <46800811+kj-9@users.noreply.github.com>
Requires-Dist: netext
Requires-Dist: rich>=14.1.0
Requires-Python: >=3.10
